pyapollos/__init__.py
pyapollos/apollo_client.py
pyapollos-0.1.5.dist-info/LICENSE
pyapollos-0.1.5.dist-info/METADATA
pyapollos-0.1.5.dist-info/WHEEL
pyapollos-0.1.5.dist-info/top_level.txt
pyapollos-0.1.5.dist-info/RECORD
