Metadata-Version: 1.1
Name: pyapollos
Version: 0.1.5
Summary: pyapollos
Home-page: https://github.com/filamoon/pyapollo
Author: monashe
Author-email: monashe@163.com
License: UNKNOWN
Platform: any
Classifier: Programming Language :: Python
Classifier: Programming Language :: Python :: 2.7
